[
    {
        "Ayah": 1,
        "Surah": 91,
        "word_ids": [
            797,
            882
        ],
        "Difficulty": 99.66251685090846
    },
    {
        "Ayah": 2,
        "Surah": 91,
        "word_ids": [
            27,
            188,
            1229
        ],
        "Difficulty": 99.9111962265074
    },
    {
        "Ayah": 3,
        "Surah": 91,
        "word_ids": [
            27,
            257,
            1525
        ],
        "Difficulty": 99.89413477288825
    },
    {
        "Ayah": 4,
        "Surah": 91,
        "word_ids": [
            27,
            1064,
            1364
        ],
        "Difficulty": 98.24382492215867
    },
    {
        "Ayah": 5,
        "Surah": 91,
        "word_ids": [
            160,
            726
        ],
        "Difficulty": 99.94785623946599
    },
    {
        "Ayah": 6,
        "Surah": 91,
        "word_ids": [
            32,
            905
        ],
        "Difficulty": 99.46784719910835
    },
    {
        "Ayah": 7,
        "Surah": 91,
        "word_ids": [
            747,
            1500
        ],
        "Difficulty": 99.6654466490696
    },
    {
        "Ayah": 8,
        "Surah": 91,
        "word_ids": [
            1108,
            1354,
            1641
        ],
        "Difficulty": 99.46985778032635
    },
    {
        "Ayah": 9,
        "Surah": 91,
        "word_ids": [
            624,
            1151
        ],
        "Difficulty": 99.75956360093382
    },
    {
        "Ayah": 10,
        "Surah": 91,
        "word_ids": [
            448,
            472
        ],
        "Difficulty": 99.26937059727756
    },
    {
        "Ayah": 11,
        "Surah": 91,
        "word_ids": [
            913,
            1263
        ],
        "Difficulty": 98.95410808532331
    },
    {
        "Ayah": 12,
        "Surah": 91,
        "word_ids": [
            26,
            137,
            788
        ],
        "Difficulty": 99.25610137244195
    },
    {
        "Ayah": 13,
        "Surah": 91,
        "word_ids": [
            61,
            61,
            555,
            704,
            1245,
            1533
        ],
        "Difficulty": 99.3110918421151
    },
    {
        "Ayah": 14,
        "Surah": 91,
        "word_ids": [
            482,
            515,
            524,
            747,
            1011,
            1263
        ],
        "Difficulty": 98.95074629554648
    },
    {
        "Ayah": 15,
        "Surah": 91,
        "word_ids": [
            444,
            1009
        ],
        "Difficulty": 99.7854644891661
    }
]